{
    "News": [
        {
            "Name": "Template 1",
            "ImgUrl": "https://dexioprotocol.github.io/DexiDragonsPublic/news/news_1.png"
        },
        {
            "Name": "Template 2",
            "ImgUrl": "https://dexioprotocol.github.io/DexiDragonsPublic/news/news_2.png"
        },
        {
            "Name": "Template 3",
            "ImgUrl": "https://dexioprotocol.github.io/DexiDragonsPublic/news/news_3.png"
        },
        {
            "Name": "Template 4",
            "ImgUrl": "https://dexioprotocol.github.io/DexiDragonsPublic/news/news_4.png"
        },
        {
            "Name": "Template 5",
            "ImgUrl": "https://dexioprotocol.github.io/DexiDragonsPublic/news/news_5.png"
        },
        {
            "Name": "Template 6",
            "ImgUrl": "https://dexioprotocol.github.io/DexiDragonsPublic/news/news_6.png"
        },
        {
            "Name": "Template 7",
            "ImgUrl": "https://dexioprotocol.github.io/DexiDragonsPublic/news/news_7.png"
        },
        {
            "Name": "Template 8",
            "ImgUrl": "https://dexioprotocol.github.io/DexiDragonsPublic/news/news_8.png"
        },
        {
            "Name": "Template 9",
            "ImgUrl": "https://dexioprotocol.github.io/DexiDragonsPublic/news/news_9.png"
        },
        {
            "Name": "Template 10",
            "ImgUrl": "https://dexioprotocol.github.io/DexiDragonsPublic/news/news_10.png"
        }
    ]
}